photos2geojson/__init__.py
photos2geojson/leaflet.html
photos2geojson/main.py
photos2geojson/simple_gist.py
photos2geojson/utils.py
photos2geojson-1.3.dist-info/DESCRIPTION.rst
photos2geojson-1.3.dist-info/METADATA
photos2geojson-1.3.dist-info/RECORD
photos2geojson-1.3.dist-info/WHEEL
photos2geojson-1.3.dist-info/entry_points.txt
photos2geojson-1.3.dist-info/metadata.json
photos2geojson-1.3.dist-info/top_level.txt
