Metadata-Version: 2.0
Name: photos2geojson
Version: 1.3
Summary: Makes geojson from EXIF data.
Home-page: https://github.com/visgean/photos2geojson
Author: Visgean Skeloru
Author-email: visgean@gmail.com
License: MIT
Keywords: photos geojson exif
Platform: UNKNOWN
Classifier: License :: OSI Approved :: MIT License
Classifier: Programming Language :: Python :: 3
Classifier: Programming Language :: Python :: 3.5
Requires-Dist: exifread
Requires-Dist: requests
